crc_calculator/__init__.py
crc_calculator/__main__.py
crc_calculator/calculator.py
crc_calculator/cli.py
crc_calculator/parser.py
crc_calculator/utils.py
crc_calculator-0.6.4.dist-info/entry_points.txt
crc_calculator-0.6.4.dist-info/LICENSE
crc_calculator-0.6.4.dist-info/WHEEL
crc_calculator-0.6.4.dist-info/METADATA
crc_calculator-0.6.4.dist-info/RECORD
