Metadata-Version: 2.1
Name: crc_calculator
Version: 0.6.4
Summary: Define program version
Author-email: junghoon-vans <junghoon.ban@gmail.com>
Requires-Python: >=3.7
Classifier: License :: OSI Approved :: MIT License
Project-URL: Source, https://github.com/junghoon-vans/crc-calculator
